simplepath/__init__.py
simplepath/constants.py
simplepath/exceptions.py
simplepath/expressions.py
simplepath/lookups.py
simplepath/lut.py
simplepath/mapper.py
simplepath/registry.py
simplepath/utils.py
simplepath-0.3.5.dist-info/DESCRIPTION.rst
simplepath-0.3.5.dist-info/METADATA
simplepath-0.3.5.dist-info/RECORD
simplepath-0.3.5.dist-info/WHEEL
simplepath-0.3.5.dist-info/metadata.json
simplepath-0.3.5.dist-info/top_level.txt
