Metadata-Version: 2.0
Name: simplepath
Version: 0.3.5
Summary: simplepath is a dictionary lookup utility/mapper with performance in mind
Home-page: https://github.com/dealertrack/simplepath
Author: Miroslav Shubernetskiy
Author-email: UNKNOWN
License: MIT
Keywords: s,i,m,p,l,e,p,a,t,h
Platform: UNKNOWN
Classifier: Intended Audience :: Developers
Classifier: Natural Language :: English
Classifier: License :: OSI Approved :: MIT License
Classifier: Programming Language :: Python
Classifier: Programming Language :: Python :: 2.7
Classifier: Programming Language :: Python :: 3
Classifier: Programming Language :: Python :: 3.4
Classifier: Development Status :: 2 - Pre-Alpha
Requires-Dist: six
Requires-Dist: setuptools
